django_pymess-0.0.1.dist-info/DESCRIPTION.rst
django_pymess-0.0.1.dist-info/METADATA
django_pymess-0.0.1.dist-info/RECORD
django_pymess-0.0.1.dist-info/WHEEL
django_pymess-0.0.1.dist-info/dependency_links.txt
django_pymess-0.0.1.dist-info/metadata.json
django_pymess-0.0.1.dist-info/top_level.txt
example/__init__.py
example/manage.py
example/dj/__init__.py
example/dj/urls.py
example/dj/wsgi.py
example/dj/apps/__init__.py
example/dj/apps/sender/__init__.py
example/dj/apps/sender/models.py
example/dj/apps/sender/tests/__init__.py
example/dj/apps/sender/tests/inputsms.py
example/dj/apps/sender/tests/outputsms.py
example/dj/apps/sender/tests/models/__init__.py
example/dj/apps/sender/tests/models/factories.py
example/dj/settings/__init__.py
example/dj/settings/base.py
example/dj/settings/settings.py
pymess/__init__.py
pymess/config.py
pymess/version.py
pymess/backend/__init__.py
pymess/backend/push/__init__.py
pymess/backend/push/dummy.py
pymess/backend/push/firebase.py
pymess/backend/sms/__init__.py
pymess/backend/sms/ats_sms_operator.py
pymess/backend/sms/dummy.py
pymess/backend/sms/sms_operator.py
pymess/backend/sms/sns.py
pymess/backend/sms/twilio.py
pymess/management/__init__.py
pymess/management/commands/__init__.py
pymess/management/commands/check_sms_delivery.py
pymess/migrations/0001_initial.py
pymess/migrations/__init__.py
pymess/models/__init__.py
pymess/models/push_notifications.py
pymess/models/sms.py
pymess/utils/__init__.py
pymess/utils/logged_requests.py
