Metadata-Version: 2.0
Name: django-pymess
Version: 0.0.1
Summary: Pymess is a Django framework for sending messages
Home-page: https://github.com/druids/django-pymess
Author: Lubos Matl,Oskar Hollman
Author-email: matllubos@gmail.com
License: LGPL
Platform: UNKNOWN
Classifier: Development Status :: 3 - Alpha
Classifier: Framework :: Django
Classifier: Intended Audience :: Developers
Classifier: License :: OSI Approved :: BSD License
Classifier: Operating System :: OS Independent
Classifier: Programming Language :: Python
Classifier: Topic :: Internet :: WWW/HTTP
Requires-Dist: django (>=1.8)
Requires-Dist: django-chamber (>=0.3.7)
